README.txt
setup.cfg
setup.py
pyogp/__init__.py
pyogp.lib.client.egg-info/PKG-INFO
pyogp.lib.client.egg-info/SOURCES.txt
pyogp.lib.client.egg-info/dependency_links.txt
pyogp.lib.client.egg-info/namespace_packages.txt
pyogp.lib.client.egg-info/not-zip-safe
pyogp.lib.client.egg-info/requires.txt
pyogp.lib.client.egg-info/top_level.txt
pyogp/lib/__init__.py
pyogp/lib/client/__init__.py
pyogp/lib/client/agent.py
pyogp/lib/client/agentdomain.py
pyogp/lib/client/agentmanager.py
pyogp/lib/client/appearance.py
pyogp/lib/client/assets.py
pyogp/lib/client/datamanager.py
pyogp/lib/client/enums.py
pyogp/lib/client/event_system.py
pyogp/lib/client/exc.py
pyogp/lib/client/groups.py
pyogp/lib/client/inventory.py
pyogp/lib/client/login.py
pyogp/lib/client/map.py
pyogp/lib/client/namevalue.py
pyogp/lib/client/objects.py
pyogp/lib/client/parcel.py
pyogp/lib/client/permissions.py
pyogp/lib/client/region.py
pyogp/lib/client/settings.py
pyogp/lib/client/visualparams.py
pyogp/lib/client/tests/__init__.py
pyogp/lib/client/tests/base.py
pyogp/lib/client/tests/config.py
pyogp/lib/client/tests/mock_xmlrpc.py
pyogp/lib/client/tests/mockup_client.py
pyogp/lib/client/tests/mockup_net.py
pyogp/lib/client/tests/test.py
pyogp/lib/client/tests/testDocTests.py
pyogp/lib/client/tests/test_agent.py
pyogp/lib/client/tests/test_appearance.py
pyogp/lib/client/tests/test_event_queue.py
pyogp/lib/client/tests/test_event_system.py
pyogp/lib/client/tests/test_inventory.py
pyogp/lib/client/tests/test_legacy_login.py
pyogp/lib/client/tests/test_namevalue.py
pyogp/lib/client/tests/test_objects.py
pyogp/lib/client/tests/test_ogp_login.py
pyogp/lib/client/tests/test_parcel.py
pyogp/lib/client/tests/test_region.py
pyogp/lib/client/tests/doctests/__init__.py